deljson/__init__.py
deljson-0.0.3.dist-info/METADATA
deljson-0.0.3.dist-info/WHEEL
deljson-0.0.3.dist-info/top_level.txt
deljson-0.0.3.dist-info/RECORD
