Metadata-Version: 2.1
Name: deljson
Version: 0.0.3
Summary: 刪除json值
Home-page: UNKNOWN
Author: seanbbear
Author-email: ccoccc14@gmail.com
License: UNKNOWN
Platform: UNKNOWN
Classifier: Development Status :: 1 - Planning
Classifier: License :: OSI Approved :: MIT License
Classifier: Operating System :: OS Independent
Requires-Python: >=3.6
